sktopt/__init__.py
sktopt/core/__init__.py
sktopt/core/derivatives.py
sktopt/core/misc.py
sktopt/core/optimizers/__init__.py
sktopt/core/optimizers/common_density.py
sktopt/core/optimizers/logmoc.py
sktopt/core/optimizers/oc.py
sktopt/core/projection.py
sktopt/core/visualization.py
sktopt/fea/__init__.py
sktopt/fea/composer.py
sktopt/fea/solver_elastic.py
sktopt/fea/solver_heat.py
sktopt/filters/__init__.py
sktopt/filters/base.py
sktopt/filters/helmholtz_filter_element.py
sktopt/filters/helmholtz_filter_nodal.py
sktopt/filters/spacial.py
sktopt/mesh/__init__.py
sktopt/mesh/loader.py
sktopt/mesh/task_common.py
sktopt/mesh/task_elastic.py
sktopt/mesh/task_heat.py
sktopt/mesh/toy_problem.py
sktopt/mesh/utils.py
sktopt/mesh/visualization.py
sktopt/tools/__init__.py
sktopt/tools/history.py
sktopt/tools/logconf.py
sktopt/tools/scheduler.py
sktopt/tools/timer.py
scikit_topt-0.3.8.dist-info/LICENSE
scikit_topt-0.3.8.dist-info/METADATA
scikit_topt-0.3.8.dist-info/WHEEL
scikit_topt-0.3.8.dist-info/RECORD
