Metadata-Version: 2.1
Name: scikit-topt
Version: 0.3.8
Summary: A lightweight, flexible Python library for topology optimization built on top of Scikit Libraries
License: Apache-2.0
Author: Kevin-Tofu
Author-email: koheitech001@gmail.com
Requires-Python: >=3.10,<3.14
Classifier: License :: OSI Approved :: Apache Software License
Classifier: Programming Language :: Python :: 3
Classifier: Programming Language :: Python :: 3.10
Classifier: Programming Language :: Python :: 3.11
Classifier: Programming Language :: Python :: 3.12
Requires-Dist: imageio (>=2.37.0,<3.0.0)
Requires-Dist: matplotlib (>=3.10.1,<4.0.0)
Requires-Dist: meshio (>=5.3.5,<6.0.0)
Requires-Dist: numba (>=0.61.0,<0.62.0)
Requires-Dist: pyamg (>=5.2.1,<6.0.0)
Requires-Dist: pyproject-toml (>=0.1.0,<0.2.0)
Requires-Dist: pyvista (>=0.44.2,<0.45.0) ; python_version >= "3.10" and python_version < "3.13"
Requires-Dist: scikit-fem (>=11.0,<12.0)
